tessbind/_version.py
tessbind/__init__.py
tessbind/utils.py
tessbind/py.typed
tessbind/_version.pyi
tessbind/manager.py
tessbind/_core.cpython-312-aarch64-linux-gnu.so
tessbind/_core.pyi
tessbind-0.13.0.dist-info/LICENSE
tessbind-0.13.0.dist-info/WHEEL
tessbind-0.13.0.dist-info/top_level.txt
tessbind-0.13.0.dist-info/METADATA
tessbind-0.13.0.dist-info/RECORD
